{"sections":{"main":{"type":"main-page","disabled":true,"settings":{"content_width":"100%"}},"e51fb5fc-05fb-406d-a60d-3ce7b067e6e8":{"type":"image-with-text-overlay","blocks":{"template--16783139111131__e51fb5fc-05fb-406d-a60d-3ce7b067e6e8-heading-1":{"type":"heading","settings":{"text":"DOWNLOAD WICKEDBONE APP","heading_tag":"h1"}},"template--16783139111131__e51fb5fc-05fb-406d-a60d-3ce7b067e6e8-subheading-1":{"type":"subheading","settings":{"text":"Dive into the wicked storm with your dog! Connect now!"}},"362d9d85-879b-46e6-9a97-94e93bb459bd":{"type":"button","settings":{"style":"fill","size":"lg","text":"iOS","url":"https:\/\/apps.apple.com\/us\/app\/wickedbone\/id1395892344","background":"","text_color":""}},"496a369f-981a-469c-bd0a-77a5ded4bac2":{"type":"button","settings":{"style":"fill","size":"lg","text":"Android","url":"https:\/\/www.cheerble.cn\/wickedbone\/Wickedbone-release_V1.5.5-55-en.apk","background":"","text_color":""}}},"block_order":["template--16783139111131__e51fb5fc-05fb-406d-a60d-3ce7b067e6e8-heading-1","template--16783139111131__e51fb5fc-05fb-406d-a60d-3ce7b067e6e8-subheading-1","362d9d85-879b-46e6-9a97-94e93bb459bd","496a369f-981a-469c-bd0a-77a5ded4bac2"],"settings":{"full_width":true,"allow_transparent_header":false,"enable_parallax":false,"image_size":"auto","image":"shopify:\/\/shop_images\/app_download_1.jpg","mobile_image":"shopify:\/\/shop_images\/app_download_1_mobile.jpg","mobile_text_position":"place-self-center text-center","desktop_text_position":"sm:place-self-start-center sm:text-center","text_color":"#ffffff","overlay_color":"#000000","overlay_opacity":10}},"5b3f14e2-a090-4c3e-9680-753c8877a487":{"type":"image-with-text-overlay","blocks":{"1323d885-b109-46ae-a461-561761fcbba5":{"type":"heading","settings":{"text":"Launch the Fun","heading_tag":"h1"}},"94d958f3-49d0-4f94-a085-946680db88dd":{"type":"richtext","settings":{"content":"<p>Personalize your dog's Wickedbone by selecting Drive or Interactive mode.<\/p>"}}},"block_order":["1323d885-b109-46ae-a461-561761fcbba5","94d958f3-49d0-4f94-a085-946680db88dd"],"settings":{"full_width":true,"allow_transparent_header":false,"enable_parallax":false,"image_size":"auto","image":"shopify:\/\/shop_images\/app_download_2.jpg","mobile_image":"shopify:\/\/shop_images\/app_download_2_mobile.jpg","mobile_text_position":"place-self-start-center text-center","desktop_text_position":"sm:place-self-start-center sm:text-center","text_color":"#1a1a1a","overlay_color":"#000000","overlay_opacity":10}}},"order":["main","e51fb5fc-05fb-406d-a60d-3ce7b067e6e8","5b3f14e2-a090-4c3e-9680-753c8877a487"]}